anovachat/__init__.py
anovachat/client.py
anovachat/exceptions.py
anovachat_py-1.0.0.dist-info/METADATA
anovachat_py-1.0.0.dist-info/WHEEL
anovachat_py-1.0.0.dist-info/top_level.txt
anovachat_py-1.0.0.dist-info/RECORD
