Metadata-Version: 2.4
Name: anovachat-py
Version: 1.0.0
Summary: A python wrapper for anova.chat
Author-email: r3tr0boy <r3tr0boy1234@proton.me>
License-Expression: MIT
Requires-Dist: httpx
